{
  "version": "7",
  "dialect": "sqlite",
  "entries": [
    {
      "idx": 0,
      "version": "6",
      "when": 1774776704765,
      "tag": "0000_worthless_luminals",
      "breakpoints": true
    },
    {
      "idx": 1,
      "version": "6",
      "when": 1775400000000,
      "tag": "0001_add_resource_log_launch_mode",
      "breakpoints": true
    },
    {
      "idx": 2,
      "version": "6",
      "when": 1775401000000,
      "tag": "0002_add_software_meta_command_line_args",
      "breakpoints": true
    },
    {
      "idx": 3,
      "version": "6",
      "when": 1775418000000,
      "tag": "0003_add_multi_image_meta_last_read_page",
      "breakpoints": true
    },
    {
      "idx": 4,
      "version": "6",
      "when": 1775421000000,
      "tag": "0004_add_multi_image_meta_translator",
      "breakpoints": true
    },
    {
      "idx": 5,
      "version": "6",
      "when": 1775572800000,
      "tag": "0005_add_asmr_meta_creaters",
      "breakpoints": true
    },
    {
      "idx": 6,
      "version": "6",
      "when": 1775616000000,
      "tag": "0006_add_asmr_meta_duration",
      "breakpoints": true
    },
    {
      "idx": 7,
      "version": "6",
      "when": 1775623200000,
      "tag": "0007_add_asmr_playback_progress",
      "breakpoints": true
    },
    {
      "idx": 8,
      "version": "7",
      "when": 1775709600000,
      "tag": "0008_add_audio_meta",
      "breakpoints": true
    },
    {
      "idx": 9,
      "version": "7",
      "when": 1775721600000,
      "tag": "0009_add_audio_meta_lyrics_path",
      "breakpoints": true
    },
    {
      "idx": 10,
      "version": "7",
      "when": 1776124800000,
      "tag": "0010_add_novel_reading_progress",
      "breakpoints": true
    },
    {
      "idx": 11,
      "version": "7",
      "when": 1776499200000,
      "tag": "0011_add_video_playback_progress",
      "breakpoints": true
    }
  ]
}
